tripplus/__init__.py
tripplus/awardplus.py
tripplus/cli.py
tripplus/py.typed
tripplus-0.1.1.dist-info/METADATA
tripplus-0.1.1.dist-info/WHEEL
tripplus-0.1.1.dist-info/entry_points.txt
tripplus-0.1.1.dist-info/licenses/LICENSE
tripplus-0.1.1.dist-info/RECORD
