Metadata-Version: 2.4
Name: tripplus
Version: 0.1.1
Summary: Add your description here
Author-email: narumi <toucans-cutouts0f@icloud.com>
License-File: LICENSE
Requires-Python: >=3.11
Requires-Dist: cloudscraper>=1.2.71
Requires-Dist: httpx>=0.27.2
Requires-Dist: pydantic>=2.10.0
